numbersII/__init__.py
numbersII/cluster.py
numbersII/challenges/D31.txt
numbersII/challenges/__init__.py
numbersII/challenges/ex7data2.mat
numbersII/challenges/worms_2d.txt
numbersII-0.0.14.dist-info/LICENSE
numbersII-0.0.14.dist-info/METADATA
numbersII-0.0.14.dist-info/WHEEL
numbersII-0.0.14.dist-info/top_level.txt
numbersII-0.0.14.dist-info/RECORD
