Metadata-Version: 2.1
Name: numbersII
Version: 0.0.14
Summary: A small library for the lesson on clustering at NumbersII
Home-page: https://github.com/ettoredangelo/numbersII
Author: ettoredangelo
Author-email: ettoredangelo@gmail.com
License: UNKNOWN
Platform: UNKNOWN
Classifier: Programming Language :: Python :: 3
Classifier: License :: OSI Approved :: MIT License
Classifier: Operating System :: OS Independent
Requires-Python: >=3.6
